odoo/addons/test_ssi_policy_mixin/README.rst
odoo/addons/test_ssi_policy_mixin/__init__.py
odoo/addons/test_ssi_policy_mixin/__manifest__.py
odoo/addons/test_ssi_policy_mixin/data/policy_template_data.xml
odoo/addons/test_ssi_policy_mixin/models/__init__.py
odoo/addons/test_ssi_policy_mixin/models/test_policy.py
odoo/addons/test_ssi_policy_mixin/models/test_policy_type.py
odoo/addons/test_ssi_policy_mixin/security/ir.model.access.csv
odoo/addons/test_ssi_policy_mixin/static/description/icon.png
odoo/addons/test_ssi_policy_mixin/views/test_policy_type_view.xml
odoo/addons/test_ssi_policy_mixin/views/test_policy_view.xml
odoo14_addon_test_ssi_policy_mixin-14.0.1.2.0.dist-info/METADATA
odoo14_addon_test_ssi_policy_mixin-14.0.1.2.0.dist-info/WHEEL
odoo14_addon_test_ssi_policy_mixin-14.0.1.2.0.dist-info/top_level.txt
odoo14_addon_test_ssi_policy_mixin-14.0.1.2.0.dist-info/RECORD
